ac/.DS_Store
ac/__init__.py
ac/api/__init__.py
ac/api/connection.py
ac/cli/__init__.py
ac/cli/cli.py
ac/cli/dataset.py
ac/cli/deployment.py
ac/cli/util.py
ac/conf/__init__.py
ac/conf/remote.py
ac/data/__init__.py
ac/data/load.py
ac/version.py
pyproject.toml
a7n_global_cli-0.0.9.dist-info/METADATA
a7n_global_cli-0.0.9.dist-info/WHEEL
a7n_global_cli-0.0.9.dist-info/entry_points.txt
a7n_global_cli-0.0.9.dist-info/RECORD
